.DS_Store
CHANGES.rst
LICENSE
README.rst
generate.py
requirements.txt
setup.py
stdeb.cfg
doc/conf.py
doc/index.rst
doc/readme_from_docstring.py
doc/requirements.txt
doc/_theme/nature/theme.conf
doc/_theme/nature/static/nature.css_t
doc/_theme/nature/static/pygments.css
doc/exts/attribute_typer.py
doc/exts/document_init_methods.py
doc/exts/resolve_default_interpreted_role.py
doc/guide/feedsub.rst
doc/guide/index.rst
doc/ref/fields.rst
doc/ref/index.rst
doc/ref/tpclient.rst
doc/ref/tpobject.rst
doc/ref/api/account.rst
doc/ref/api/apikey.rst
doc/ref/api/application.rst
doc/ref/api/asset.rst
doc/ref/api/assetextendedcontent.rst
doc/ref/api/assetref.rst
doc/ref/api/assetsource.rst
doc/ref/api/audio.rst
doc/ref/api/audiolink.rst
doc/ref/api/authtoken.rst
doc/ref/api/blog.rst
doc/ref/api/blogcommentingsettings.rst
doc/ref/api/blogstats.rst
doc/ref/api/comment.rst
doc/ref/api/commenttreeitem.rst
doc/ref/api/containerref.rst
doc/ref/api/endpoint.rst
doc/ref/api/entity.rst
doc/ref/api/event.rst
doc/ref/api/externalfeedsubscription.rst
doc/ref/api/favorite.rst
doc/ref/api/feedbackstatus.rst
doc/ref/api/group.rst
doc/ref/api/imagelink.rst
doc/ref/api/index.rst
doc/ref/api/link.rst
doc/ref/api/objectproperty.rst
doc/ref/api/objecttype.rst
doc/ref/api/page.rst
doc/ref/api/photo.rst
doc/ref/api/post.rst
doc/ref/api/postbyemailaddress.rst
doc/ref/api/publicationstatus.rst
doc/ref/api/relationship.rst
doc/ref/api/relationshipstatus.rst
doc/ref/api/user.rst
doc/ref/api/userprofile.rst
doc/ref/api/video.rst
doc/ref/api/videolink.rst
doc/tut/auth.rst
doc/tut/index.rst
doc/tut/start.rst
tests/__init__.py
tests/batch-error.py
tests/onebyone.png
tests/requirements.txt
tests/test_api.py
tests/test_tpclient.py
tests/test_tpobject.py
tests/test_typepad.py
tests/utils.py
typepad/__init__.py
typepad/api.py
typepad/fields.py
typepad/tpclient.py
typepad/tpobject.py